bounced/__init__.py
bounced/bounced.py
bounced/tests/test_bounced.py
bounced/tests/bounce_email/bounces/bounce-auto-respond.eml
bounced/tests/bounce_email/bounces/malformed_bounce_01.eml
bounced/tests/bounce_email/bounces/tt_1234175799.eml
bounced/tests/bounce_email/bounces/tt_1234177688.eml
bounced/tests/bounce_email/bounces/tt_1234210655.eml
bounced/tests/bounce_email/bounces/tt_1234211357.eml
bounced/tests/bounce_email/bounces/tt_1234211929.eml
bounced/tests/bounce_email/bounces/tt_1234211931.eml
bounced/tests/bounce_email/bounces/tt_1234211932.eml
bounced/tests/bounce_email/bounces/tt_1234241665.eml
bounced/tests/bounce_email/bounces/tt_1234285532.eml
bounced/tests/bounce_email/bounces/tt_1234285668.eml
bounced/tests/bounce_email/bounces/tt_bounce_01.eml
bounced/tests/bounce_email/bounces/tt_bounce_02.eml
bounced/tests/bounce_email/bounces/tt_bounce_03.eml
bounced/tests/bounce_email/bounces/tt_bounce_04.eml
bounced/tests/bounce_email/bounces/tt_bounce_05.eml
bounced/tests/bounce_email/bounces/tt_bounce_06.eml
bounced/tests/bounce_email/bounces/tt_bounce_07.eml
bounced/tests/bounce_email/bounces/tt_bounce_08.eml
bounced/tests/bounce_email/bounces/tt_bounce_09.eml
bounced/tests/bounce_email/bounces/tt_bounce_10.eml
bounced/tests/bounce_email/bounces/tt_bounce_11.eml
bounced/tests/bounce_email/bounces/tt_bounce_12_soft.eml
bounced/tests/bounce_email/bounces/tt_bounce_13.eml
bounced/tests/bounce_email/bounces/tt_bounce_14.eml
bounced/tests/bounce_email/bounces/tt_bounce_15.eml
bounced/tests/bounce_email/bounces/tt_bounce_16.eml
bounced/tests/bounce_email/bounces/tt_bounce_17.eml
bounced/tests/bounce_email/bounces/tt_bounce_18.eml
bounced/tests/bounce_email/bounces/tt_bounce_19.eml
bounced/tests/bounce_email/bounces/tt_bounce_20.eml
bounced/tests/bounce_email/bounces/tt_bounce_21.eml
bounced/tests/bounce_email/bounces/tt_bounce_22.eml
bounced/tests/bounce_email/bounces/tt_bounce_23.eml
bounced/tests/bounce_email/bounces/tt_bounce_24.eml
bounced-0.3.0.dist-info/LICENSE
bounced-0.3.0.dist-info/METADATA
bounced-0.3.0.dist-info/WHEEL
bounced-0.3.0.dist-info/top_level.txt
bounced-0.3.0.dist-info/RECORD
